typed_everywhere/__init__.py
typed_everywhere/typed_everywhere.py
typed_everywhere-1.3.0.dist-info/METADATA
typed_everywhere-1.3.0.dist-info/WHEEL
typed_everywhere-1.3.0.dist-info/RECORD
