Metadata-Version: 2.4
Name: typed-everywhere
Version: 1.3.0
Summary: Runtime type checking and not only for function arguments and class variables but even for the ordinary local and global variables!
Project-URL: Homepage, https://github.com/pyhacks/typed-everywhere
Author-email: pyhacks <enginyildirim111@gmail.com>
Keywords: checking,dynamic,runtime,type
Requires-Dist: assign-overload
Requires-Dist: typeguard
Requires-Dist: wrapt
